bearlibterminal/__init__.py
bearlibterminal/libBearLibTerminal.dylib
bearlibterminal/terminal.py
bearlibterminal-0.15.8.dist-info/METADATA
bearlibterminal-0.15.8.dist-info/WHEEL
bearlibterminal-0.15.8.dist-info/top_level.txt
bearlibterminal-0.15.8.dist-info/RECORD
