Metadata-Version: 2.1
Name: bearlibterminal
Version: 0.15.8
Summary: BearLibTerminal is a pseudoterminal window library
Home-page: http://foo.wyrd.name/en:bearlibterminal
Author: Alexander Malinin
Author-email: cfyzium@gmail.com
License: MIT
Keywords: roguelike,terminal,ascii,tiles,unicode
Platform: Windows
Platform: Linux
Platform: Mac OS X
Classifier: Development Status :: 4 - Beta
Classifier: Environment :: Win32 (MS Windows)
Classifier: Environment :: X11 Applications
Classifier: Environment :: MacOS X :: Cocoa
Classifier: Intended Audience :: Developers
Classifier: License :: OSI Approved :: MIT License
Classifier: Natural Language :: English
Classifier: Operating System :: Microsoft :: Windows
Classifier: Operating System :: POSIX :: Linux
Classifier: Operating System :: MacOS :: MacOS X
Classifier: Programming Language :: Python :: 2
Classifier: Programming Language :: Python :: 3
Classifier: Topic :: Games/Entertainment
Classifier: Topic :: Multimedia :: Graphics
Classifier: Topic :: Software Development :: Libraries
